b_cfn_elasticsearch_index/__init__.py
b_cfn_elasticsearch_index/function.py
b_cfn_elasticsearch_index/resource.py
b_cfn_elasticsearch_index/source/__init__.py
b_cfn_elasticsearch_index/source/action.py
b_cfn_elasticsearch_index/source/cfnresponse.py
b_cfn_elasticsearch_index/source/index.py
b_cfn_elasticsearch_index-0.0.6.dist-info/LICENSE
b_cfn_elasticsearch_index-0.0.6.dist-info/METADATA
b_cfn_elasticsearch_index-0.0.6.dist-info/WHEEL
b_cfn_elasticsearch_index-0.0.6.dist-info/top_level.txt
b_cfn_elasticsearch_index-0.0.6.dist-info/RECORD
