Metadata-Version: 2.1
Name: b-cfn-elasticsearch-index
Version: 0.0.6
Summary: AWS CDK based custom resource that manages an Elasticsearch index.
Home-page: https://github.com/biomapas/B.CfnElasticsearchIndex.git
Author: Ignas Kiela
Author-email: ignas.kiela@biomapas.com
License: Apache License 2.0
Keywords: AWS CDK Lambda Layer Elasticsearch Index
Platform: UNKNOWN
Classifier: Programming Language :: Python :: 3
Classifier: Operating System :: OS Independent
Requires-Dist: aws-cdk.core (<2.0.0,>=1.54.0)
Requires-Dist: aws-cdk.aws-lambda (<2.0.0,>=1.54.0)
Requires-Dist: aws-cdk.aws-elasticsearch (<2.0.0,>=1.54.0)
Requires-Dist: b-elasticsearch-layer (<1.0.0,>=0.0.1)
